[ {
  "fecha" : "2024-08-31",
  "indicativo" : "8096",
  "nombre" : "CUENCA",
  "provincia" : "CUENCA",
  "altitud" : "949",
  "tmed" : "22,9",
  "prec" : "0,0",
  "tmin" : "17,2",
  "horatmin" : "07:00",
  "tmax" : "28,6",
  "horatmax" : "14:20",
  "dir" : "15",
  "velmedia" : "2,5",
  "racha" : "10,0",
  "horaracha" : "19:00",
  "sol" : "4,1",
  "presMax" : "910,9",
  "horaPresMax" : "01",
  "presMin" : "906,8",
  "horaPresMin" : "19",
  "hrMedia" : "64",
  "hrMax" : "85",
  "horaHrMax" : "07:10",
  "hrMin" : "43",
  "horaHrMin" : "14:00"
} ]