[ {
  "fecha" : "2024-07-19",
  "indicativo" : "5783",
  "nombre" : "SEVILLA AEROPUERTO",
  "provincia" : "SEVILLA",
  "altitud" : "34",
  "tmed" : "31,2",
  "prec" : "0,0",
  "tmin" : "21,4",
  "horatmin" : "05:39",
  "tmax" : "41,0",
  "horatmax" : "16:19",
  "dir" : "23",
  "velmedia" : "3,3",
  "racha" : "11,4",
  "horaracha" : "18:08",
  "sol" : "12,3",
  "presMax" : "1014,2",
  "horaPresMax" : "Varias",
  "presMin" : "1009,8",
  "horaPresMin" : "17",
  "hrMedia" : "36",
  "hrMax" : "73",
  "horaHrMax" : "Varias",
  "hrMin" : "19",
  "horaHrMin" : "14:49"
} ]