[ {
  "fecha" : "2024-07-20",
  "indicativo" : "5530E",
  "nombre" : "GRANADA AEROPUERTO",
  "provincia" : "GRANADA",
  "altitud" : "567",
  "tmed" : "29,4",
  "prec" : "0,0",
  "tmin" : "19,3",
  "horatmin" : "05:56",
  "tmax" : "39,6",
  "horatmax" : "14:57",
  "dir" : "28",
  "velmedia" : "4,7",
  "racha" : "12,5",
  "horaracha" : "13:46",
  "sol" : "13,3",
  "presMax" : "951,4",
  "horaPresMax" : "00",
  "presMin" : "945,7",
  "horaPresMin" : "17",
  "hrMedia" : "26",
  "hrMax" : "54",
  "horaHrMax" : "06:53",
  "hrMin" : "11",
  "horaHrMin" : "Varias"
} ]