[ {
  "fecha" : "2024-09-02",
  "indicativo" : "5530E",
  "nombre" : "GRANADA AEROPUERTO",
  "provincia" : "GRANADA",
  "altitud" : "567",
  "tmed" : "26,6",
  "prec" : "0,0",
  "tmin" : "19,2",
  "horatmin" : "05:32",
  "tmax" : "34,0",
  "horatmax" : "14:27",
  "dir" : "29",
  "velmedia" : "3,1",
  "racha" : "11,7",
  "horaracha" : "13:32",
  "sol" : "12,0",
  "presMax" : "949,2",
  "horaPresMax" : "Varias",
  "presMin" : "945,8",
  "horaPresMin" : "16",
  "hrMedia" : "45",
  "hrMax" : "83",
  "horaHrMax" : "Varias",
  "hrMin" : "26",
  "horaHrMin" : "Varias"
} ]