[ {
  "fecha" : "2024-08-22",
  "indicativo" : "8096",
  "nombre" : "CUENCA",
  "provincia" : "CUENCA",
  "altitud" : "949",
  "tmed" : "27,2",
  "prec" : "20,0",
  "tmin" : "19,6",
  "horatmin" : "15:20",
  "tmax" : "34,7",
  "horatmax" : "13:30",
  "dir" : "11",
  "velmedia" : "1,4",
  "racha" : "10,8",
  "horaracha" : "15:20",
  "sol" : "6,1",
  "presMax" : "910,7",
  "horaPresMax" : "00",
  "presMin" : "907,7",
  "horaPresMin" : "18",
  "hrMedia" : "57",
  "hrMax" : "80",
  "horaHrMax" : "22:20",
  "hrMin" : "25",
  "horaHrMin" : "12:40"
} ]