[ {
  "fecha" : "2024-08-05",
  "indicativo" : "8500A",
  "nombre" : "CASTELLÓ - ALMASSORA",
  "provincia" : "CASTELLON",
  "altitud" : "43",
  "tmed" : "28,5",
  "prec" : "0,0",
  "tmin" : "24,2",
  "horatmin" : "05:00",
  "tmax" : "32,8",
  "horatmax" : "13:20",
  "dir" : "11",
  "velmedia" : "1,9",
  "racha" : "8,1",
  "horaracha" : "15:50",
  "sol" : "7,6",
  "presMax" : "1008,2",
  "horaPresMax" : "00",
  "presMin" : "1005,5",
  "horaPresMin" : "16",
  "hrMedia" : "66",
  "hrMax" : "82",
  "horaHrMax" : "23:30",
  "hrMin" : "62",
  "horaHrMin" : "11:30"
} ]