[ {
  "fecha" : "2024-08-06",
  "indicativo" : "9898",
  "nombre" : "HUESCA, AEROPUERTO",
  "provincia" : "HUESCA",
  "altitud" : "546",
  "tmed" : "28,4",
  "prec" : "0,0",
  "tmin" : "20,9",
  "horatmin" : "04:50",
  "tmax" : "36,0",
  "horatmax" : "16:00",
  "dir" : "14",
  "velmedia" : "2,5",
  "racha" : "8,3",
  "horaracha" : "11:10",
  "sol" : "12,0",
  "presMax" : "950,0",
  "horaPresMax" : "Varias",
  "presMin" : "946,5",
  "horaPresMin" : "17",
  "hrMedia" : "47",
  "hrMax" : "75",
  "horaHrMax" : "04:30",
  "hrMin" : "28",
  "horaHrMin" : "16:40"
} ]