[ {
  "fecha" : "2024-08-21",
  "indicativo" : "3195",
  "nombre" : "MADRID, RETIRO",
  "provincia" : "MADRID",
  "altitud" : "667",
  "tmed" : "28,8",
  "prec" : "0,0",
  "tmin" : "21,1",
  "horatmin" : "Varias",
  "tmax" : "36,4",
  "horatmax" : "14:40",
  "dir" : "04",
  "velmedia" : "1,9",
  "racha" : "11,9",
  "horaracha" : "03:50",
  "presMax" : "941,1",
  "horaPresMax" : "Varias",
  "presMin" : "936,6",
  "horaPresMin" : "17",
  "hrMedia" : "34",
  "hrMax" : "56",
  "horaHrMax" : "06:30",
  "hrMin" : "16",
  "horaHrMin" : "17:30"
} ]