[ {
  "fecha" : "2024-09-24",
  "indicativo" : "6325O",
  "nombre" : "ALMERÍA AEROPUERTO",
  "provincia" : "ALMERIA",
  "altitud" : "21",
  "tmed" : "23,2",
  "prec" : "0,0",
  "tmin" : "20,0",
  "horatmin" : "05:19",
  "tmax" : "26,4",
  "horatmax" : "15:06",
  "dir" : "24",
  "velmedia" : "4,7",
  "racha" : "12,8",
  "horaracha" : "15:50",
  "sol" : "4,8",
  "presMax" : "1012,8",
  "horaPresMax" : "23",
  "presMin" : "1009,9",
  "horaPresMin" : "16",
  "hrMedia" : "62",
  "hrMax" : "88",
  "horaHrMax" : "05:15",
  "hrMin" : "48",
  "horaHrMin" : "07:53"
} ]