[ {
  "fecha" : "2024-09-21",
  "indicativo" : "5402",
  "nombre" : "CÓRDOBA AEROPUERTO",
  "provincia" : "CORDOBA",
  "altitud" : "90",
  "tmed" : "24,2",
  "prec" : "0,0",
  "tmin" : "19,5",
  "horatmin" : "Varias",
  "tmax" : "29,0",
  "horatmax" : "14:02",
  "dir" : "23",
  "velmedia" : "3,9",
  "racha" : "11,4",
  "horaracha" : "16:33",
  "sol" : "10,5",
  "presMax" : "1005,1",
  "horaPresMax" : "Varias",
  "presMin" : "1001,3",
  "horaPresMin" : "15",
  "hrMedia" : "52",
  "hrMax" : "77",
  "horaHrMax" : "Varias",
  "hrMin" : "30",
  "horaHrMin" : "13:39"
} ]