[ {
  "fecha" : "2024-08-28",
  "indicativo" : "5783",
  "nombre" : "SEVILLA AEROPUERTO",
  "provincia" : "SEVILLA",
  "altitud" : "34",
  "tmed" : "28,8",
  "prec" : "0,0",
  "tmin" : "24,1",
  "horatmin" : "05:56",
  "tmax" : "33,4",
  "horatmax" : "14:53",
  "dir" : "99",
  "velmedia" : "3,9",
  "racha" : "9,2",
  "horaracha" : "Varias",
  "sol" : "11,0",
  "presMax" : "1011,0",
  "horaPresMax" : "Varias",
  "presMin" : "1007,3",
  "horaPresMin" : "18",
  "hrMedia" : "60",
  "hrMax" : "80",
  "horaHrMax" : "Varias",
  "hrMin" : "47",
  "horaHrMin" : "14:53"
} ]